bonfire/__init__.py
bonfire/_version.py
bonfire/cli.py
bonfire/config.py
bonfire/dateutils.py
bonfire/formats.py
bonfire/graylog_api.py
bonfire/output.py
bonfire/utils.py
bonfire-0.0.8.data/data/AUTHORS.rst
bonfire-0.0.8.data/data/LICENSE.txt
bonfire-0.0.8.data/data/README.rst
bonfire-0.0.8.data/data/requirements.txt
bonfire-0.0.8.dist-info/AUTHORS.rst
bonfire-0.0.8.dist-info/LICENSE.txt
bonfire-0.0.8.dist-info/METADATA
bonfire-0.0.8.dist-info/WHEEL
bonfire-0.0.8.dist-info/entry_points.txt
bonfire-0.0.8.dist-info/namespace_packages.txt
bonfire-0.0.8.dist-info/top_level.txt
bonfire-0.0.8.dist-info/RECORD
