Metadata-Version: 2.1
Name: bonfire
Version: 0.0.8
Summary: Add a small description here!
Home-page: http://...
Author: Malte Harder
Author-email: malte.harder@blue-yonder.com
License: new BSD
Platform: UNKNOWN
Classifier: Development Status :: 3 - Alpha
Classifier: Topic :: Utilities
Classifier: Programming Language :: Python
Requires-Dist: click (<7,>=3.3)
Requires-Dist: keyring (<21,>=9)
Requires-Dist: parsedatetime (<3,>=1.4)
Requires-Dist: python-dateutil (<3,>=2.4.1)
Requires-Dist: requests (<3.0,>=2.4.3)
Requires-Dist: arrow (<0.16,>=0.13.0)
Requires-Dist: termcolor (==1.1.0)
Requires-Dist: six (>=1.9.0)
